depthcharge/__init__.py
depthcharge/constants.py
depthcharge/feedforward.py
depthcharge/mixins.py
depthcharge/primitives.py
depthcharge/testing.py
depthcharge/utils.py
depthcharge/version.py
depthcharge/data/__init__.py
depthcharge/data/analyte_datasets.py
depthcharge/data/arrow.py
depthcharge/data/fields.py
depthcharge/data/parsers.py
depthcharge/data/preprocessing.py
depthcharge/data/spectrum_datasets.py
depthcharge/encoders/__init__.py
depthcharge/encoders/sinusoidal.py
depthcharge/tokenizers/__init__.py
depthcharge/tokenizers/molecules.py
depthcharge/tokenizers/peptides.py
depthcharge/tokenizers/tokenizer.py
depthcharge/transformers/__init__.py
depthcharge/transformers/analytes.py
depthcharge/transformers/spectra.py
depthcharge_ms-0.4.9.dist-info/licenses/LICENSE
depthcharge_ms-0.4.9.dist-info/METADATA
depthcharge_ms-0.4.9.dist-info/WHEEL
depthcharge_ms-0.4.9.dist-info/top_level.txt
depthcharge_ms-0.4.9.dist-info/RECORD
